fastest/__init__.py
fastest/__main__.py
fastest/bodies/__init__.py
fastest/bodies/test_case_template_builder.py
fastest/cli/__init__.py
fastest/cli/args.py
fastest/code_assets/__init__.py
fastest/code_assets/function.py
fastest/code_assets/keywords.py
fastest/code_assets/naive_case_detector.py
fastest/constants.py
fastest/file_handler/__init__.py
fastest/file_handler/coverage_path.py
fastest/file_handler/create_test_command.py
fastest/file_handler/ignore_paths.py
fastest/file_handler/make_test_dir.py
fastest/file_handler/read_file.py
fastest/file_handler/run_coverage.py
fastest/file_handler/run_tests.py
fastest/logger/__init__.py
fastest/logger/logger.py
fastest/test_compiler/__init__.py
fastest/test_compiler/compile_tests.py
fastest/test_compiler/test_writer.py
fastest/type/__init__.py
fastest/type/type_inference.py
fastest/type/type_usage_patterns.py
fastest/utils.py
fastest-0.3.1.dist-info/entry_points.txt
fastest-0.3.1.dist-info/WHEEL
fastest-0.3.1.dist-info/METADATA
fastest-0.3.1.dist-info/RECORD
