Metadata-Version: 2.1
Name: fastest
Version: 0.3.1
Summary: Automate tests via docstrings and more
Home-page: https://github.com/AmreshVenugopal/fastest
License: MIT
Author: AmreshVenugopal
Author-email: amresh.venugopal@gmail.com
Requires-Python: >=3.5,<4.0
Classifier: License :: OSI Approved :: MIT License
Classifier: Programming Language :: Python :: 3
Classifier: Programming Language :: Python :: 3.5
Classifier: Programming Language :: Python :: 3.6
Classifier: Programming Language :: Python :: 3.7
Requires-Dist: coloredlogs (>=10.0,<11.0)
Requires-Dist: coverage (>=4.5,<5.0)
Requires-Dist: pytest (>=4.2,<5.0)
Requires-Dist: pytest-cov (>=2.6,<3.0)
Requires-Dist: watchdog (>=0.9.0,<0.10.0)
Project-URL: Repository, https://github.com/AmreshVenugopal/fastest
